similib/__init__.py
similib/cmd.py
similib/conf.py
similib/date_and_time.py
similib/exceptions.py
similib/getDriver.py
similib/hide_security.py
similib/mongodb.py
similib/trans.py
similib/upload.py
similib/webdriver.py
similib/xpath.py
similib-1.5.dist-info/LICENSE
similib-1.5.dist-info/METADATA
similib-1.5.dist-info/WHEEL
similib-1.5.dist-info/top_level.txt
similib-1.5.dist-info/RECORD
