Metadata-Version: 2.1
Name: similib
Version: 1.5
Summary: simi的自用包！
Author: simi
Author-email: 1820407818@qq.com
License: UNKNOWN
Platform: UNKNOWN
Classifier: Programming Language :: Python :: 3
Classifier: License :: OSI Approved :: MIT License
Classifier: Operating System :: OS Independent
Requires-Python: >=3
License-File: LICENSE
Requires-Dist: pymongo
Requires-Dist: selenium
Requires-Dist: pytz
Requires-Dist: requests
Requires-Dist: packaging
